pkg/__init__.py
pkg/pkg.py
debug_world1_20210308-0.0.1.dist-info/METADATA
debug_world1_20210308-0.0.1.dist-info/WHEEL
debug_world1_20210308-0.0.1.dist-info/top_level.txt
debug_world1_20210308-0.0.1.dist-info/RECORD
