Metadata-Version: 2.1
Name: debug-world1-20210308
Version: 0.0.1
Summary: PyPI Tutorial
Home-page: UNKNOWN
Author: JINKUN
Author-email: author@example.com
License: UNKNOWN
Platform: UNKNOWN
Classifier: Programming Language :: Python :: 3
Classifier: Operating System :: OS Independent
